[{"code": "012330", "name": "현대모비스", "exit_date": "2026-05-29", "exit_price": 779000, "reason": "모멘텀약화(+13.4%)", "d3": 761000, "d5": 759000, "d10": 570000, "d20": null}, {"code": "005930", "name": "삼성전자", "exit_date": "2026-06-01", "exit_price": 343000, "reason": "모멘텀약화(+13.4%)", "d3": 351500, "d5": 302500, "d10": 299000, "d20": null}, {"code": "018260", "name": "삼성에스디에스", "exit_date": "2026-06-02", "exit_price": 286500, "reason": "손절(캔들확인)", "d3": 252500, "d5": 225000, "d10": 237000, "d20": null}, {"code": "034220", "name": "LG디스플레이", "exit_date": "2026-06-04", "exit_price": 15830, "reason": "손절(캔들확인)", "d3": 12910, "d5": 12910, "d10": null, "d20": null}, {"code": "009150", "name": "삼성전기", "exit_date": "2026-06-04", "exit_price": 1716000, "reason": "손절(캔들확인)", "d3": 1805000, "d5": 1805000, "d10": null, "d20": null}, {"code": "000660", "name": "SK하이닉스", "exit_date": "2026-06-05", "exit_price": 2095000, "reason": "손절(캔들확인)", "d3": 2048000, "d5": 2048000, "d10": null, "d20": null}, {"code": "000650", "name": "천일고속", "exit_date": "2026-06-05", "exit_price": 232500, "reason": "손절(캔들확인)", "d3": 192000, "d5": 192000, "d10": null, "d20": null}, {"code": "084670", "name": "동양고속", "exit_date": "2026-06-05", "exit_price": 44650, "reason": "손절(캔들확인)", "d3": 37100, "d5": 37100, "d10": null, "d20": null}, {"code": "023530", "name": "롯데쇼핑", "exit_date": "2026-06-10", "exit_price": 192000, "reason": "모멘텀약화(+10.5%)", "d3": null, "d5": null, "d10": null, "d20": null}, {"code": "009150", "name": "삼성전기", "exit_date": "2026-06-10", "exit_price": 1829000, "reason": "본전보호(캔들확인)", "d3": null, "d5": null, "d10": null, "d20": null}]